devopsmind/__init__.py
devopsmind/__main__.py
devopsmind/badges.py
devopsmind/constants.py
devopsmind/doctor.py
devopsmind/entrypoint.py
devopsmind/help.py
devopsmind/profiles.py
devopsmind/progress.py
devopsmind/state.py
devopsmind/state_normalizer.py
devopsmind/stats.py
devopsmind/streak.py
devopsmind/submit.py
devopsmind/utils.py
devopsmind/achievements/__init__.py
devopsmind/achievements/cross_skill.yaml
devopsmind/achievements/difficulty.yaml
devopsmind/achievements/labs.yaml
devopsmind/achievements/milestones.yaml
devopsmind/achievements/rank.yaml
devopsmind/achievements/schema.py
devopsmind/achievements/secret.yaml
devopsmind/achievements/skills.yaml
devopsmind/achievements/stacks.yaml
devopsmind/achievements/streak.yaml
devopsmind/achievements/__pycache__/__init__.cpython-312.pyc
devopsmind/cache/cache.py
devopsmind/cache/runtime.py
devopsmind/cli/__init__.py
devopsmind/cli/cli.py
devopsmind/cli/outbox_cli.py
devopsmind/cli/runtime_registry.py
devopsmind/completion/__init__.py
devopsmind/completion/autocomplete.py
devopsmind/completion/generator.py
devopsmind/completion/helper.py
devopsmind/completion/registry.py
devopsmind/engine/describe.py
devopsmind/engine/engine.py
devopsmind/engine/hint.py
devopsmind/engine/start.py
devopsmind/engine/ui_icons.py
devopsmind/engine/ui_secret.py
devopsmind/engine/validator.py
devopsmind/handlers/__init__.py
devopsmind/handlers/activation_handler.py
devopsmind/handlers/command_handler.py
devopsmind/handlers/command_result.py
devopsmind/handlers/id_normalizer.py
devopsmind/handlers/init_handler.py
devopsmind/handlers/lab_gate.py
devopsmind/handlers/lab_utils.py
devopsmind/handlers/logout_handler.py
devopsmind/handlers/progress_renderer.py
devopsmind/handlers/project_handler.py
devopsmind/handlers/project_xp.py
devopsmind/handlers/reset_handler.py
devopsmind/handlers/resume.py
devopsmind/handlers/stacks_handler.py
devopsmind/handlers/start_env.py
devopsmind/handlers/start_handler.py
devopsmind/handlers/streak_handler.py
devopsmind-1.1.1.dist-info/licenses/LICENSE
devopsmind-1.1.1.dist-info/METADATA
devopsmind-1.1.1.dist-info/WHEEL
devopsmind-1.1.1.dist-info/entry_points.txt
devopsmind-1.1.1.dist-info/top_level.txt
devopsmind-1.1.1.dist-info/RECORD
