Metadata-Version: 2.4
Name: devopsmind
Version: 1.1.1
Summary: Hands-on, DevOps learning platform with real labs and local sandbox execution.
Author-email: InfraForge Labs <devopsmind@infraforgelabs.com>
Requires-Python: >=3.9
License-File: LICENSE
Requires-Dist: python-hcl2
Requires-Dist: pyyaml
Requires-Dist: rich
Requires-Dist: click
Requires-Dist: colorama
Requires-Dist: requests
Requires-Dist: packaging>=23.0
Requires-Dist: reportlab>=4.0
Requires-Dist: qrcode[pil]>=7.4
Dynamic: license-file
